rapidgui/__init__.py
rapidgui/quickGui.py
rapidgui-0.0.13b0.dist-info/METADATA
rapidgui-0.0.13b0.dist-info/WHEEL
rapidgui-0.0.13b0.dist-info/licenses/LICENSE
rapidgui-0.0.13b0.dist-info/RECORD
