Metadata-Version: 2.1
Name: rapidgui
Version: 0.0.13b0
Summary: no fuss rapid gui for quick and easy development
License: MIT License
License-File: LICENSE
Classifier: License :: OSI Approved :: MIT License
Classifier: Operating System :: OS Independent
Classifier: Programming Language :: Python :: 3
